easymysql/__init__.py
easymysql/abstracts.py
easymysql/authentication.py
easymysql/catch23.py
easymysql/charsets.py
easymysql/connector.py
easymysql/constants.py
easymysql/conversion.py
easymysql/custom_types.py
easymysql/dbapi.py
easymysql/errorcode.py
easymysql/errors.py
easymysql/network.py
easymysql/optionfiles.py
easymysql/pooling.py
easymysql/protocol.py
easymysql/re_patterns.py
easymysql/utils.py
easymysql/locales/__init__.py
easymysql/locales/eng/__init__.py
easymysql/locales/eng/client_error.py
py_mysql_client-0.0.0.2.dist-info/METADATA
py_mysql_client-0.0.0.2.dist-info/WHEEL
py_mysql_client-0.0.0.2.dist-info/top_level.txt
py_mysql_client-0.0.0.2.dist-info/RECORD
