Metadata-Version: 2.1
Name: py-mysql-client
Version: 0.0.0.2
Summary: A lite python mysql driver
Home-page: https://github.com/stellaye
Author: lindaye
Author-email: 454784911@qq.com
License: UNKNOWN
Platform: UNKNOWN
